wiki_bot.py
wiki_bot-1.3.1.dist-info/METADATA
wiki_bot-1.3.1.dist-info/RECORD
wiki_bot-1.3.1.dist-info/WHEEL
wiki_bot-1.3.1.dist-info/top_level.txt
